{
  "m_Version": 12,
  "DisplayName": "RenegadeGear_Vests",
  "Icon": "Deliver",
  "Color": "FBFCFEFF",
  "InitStockPercent": 75.0,
  "IsExchange": 0,
  "Items": [
    {
      "ClassName": "renegade_blackbluecamosmershvest",
      "MaxPriceThreshold": 35000,
      "MinPriceThreshold": 22750,
      "SellPricePercent": -1,
      "MaxStockThreshold": 1,
      "MinStockThreshold": 1,
      "QuantityPercent": -1,
      "SpawnAttachments": [],
      "Variants": []
    },
    {
      "ClassName": "renegade_blackbluedarkplatecarrier",
      "MaxPriceThreshold": 35000,
      "MinPriceThreshold": 22750,
      "SellPricePercent": -1,
      "MaxStockThreshold": 1,
      "MinStockThreshold": 1,
      "QuantityPercent": -1,
      "SpawnAttachments": [],
      "Variants": []
    },
    {
      "ClassName": "renegade_blackbluedarkpressvest",
      "MaxPriceThreshold": 35000,
      "MinPriceThreshold": 22750,
      "SellPricePercent": -1,
      "MaxStockThreshold": 1,
      "MinStockThreshold": 1,
      "QuantityPercent": -1,
      "SpawnAttachments": [],
      "Variants": []
    },
    {
      "ClassName": "renegade_blackbluedarksmershvest",
      "MaxPriceThreshold": 35000,
      "MinPriceThreshold": 22750,
      "SellPricePercent": -1,
      "MaxStockThreshold": 1,
      "MinStockThreshold": 1,
      "QuantityPercent": -1,
      "SpawnAttachments": [],
      "Variants": []
    },
    {
      "ClassName": "renegade_blackblueplatecarrier",
      "MaxPriceThreshold": 35000,
      "MinPriceThreshold": 22750,
      "SellPricePercent": -1,
      "MaxStockThreshold": 1,
      "MinStockThreshold": 1,
      "QuantityPercent": -1,
      "SpawnAttachments": [],
      "Variants": []
    },
    {
      "ClassName": "renegade_blackbluepressvest",
      "MaxPriceThreshold": 35000,
      "MinPriceThreshold": 22750,
      "SellPricePercent": -1,
      "MaxStockThreshold": 1,
      "MinStockThreshold": 1,
      "QuantityPercent": -1,
      "SpawnAttachments": [],
      "Variants": []
    },
    {
      "ClassName": "renegade_blackbluesmershvest",
      "MaxPriceThreshold": 35000,
      "MinPriceThreshold": 22750,
      "SellPricePercent": -1,
      "MaxStockThreshold": 1,
      "MinStockThreshold": 1,
      "QuantityPercent": -1,
      "SpawnAttachments": [],
      "Variants": []
    },
    {
      "ClassName": "renegade_blackcamoplatecarrier",
      "MaxPriceThreshold": 35000,
      "MinPriceThreshold": 22750,
      "SellPricePercent": -1,
      "MaxStockThreshold": 1,
      "MinStockThreshold": 1,
      "QuantityPercent": -1,
      "SpawnAttachments": [],
      "Variants": []
    },
    {
      "ClassName": "renegade_blackcamopressvest",
      "MaxPriceThreshold": 35000,
      "MinPriceThreshold": 22750,
      "SellPricePercent": -1,
      "MaxStockThreshold": 1,
      "MinStockThreshold": 1,
      "QuantityPercent": -1,
      "SpawnAttachments": [],
      "Variants": []
    },
    {
      "ClassName": "renegade_blackcamosmershvest",
      "MaxPriceThreshold": 35000,
      "MinPriceThreshold": 22750,
      "SellPricePercent": -1,
      "MaxStockThreshold": 1,
      "MinStockThreshold": 1,
      "QuantityPercent": -1,
      "SpawnAttachments": [],
      "Variants": []
    },
    {
      "ClassName": "renegade_blackgreenplatecarrier",
      "MaxPriceThreshold": 35000,
      "MinPriceThreshold": 22750,
      "SellPricePercent": -1,
      "MaxStockThreshold": 1,
      "MinStockThreshold": 1,
      "QuantityPercent": -1,
      "SpawnAttachments": [],
      "Variants": []
    },
    {
      "ClassName": "renegade_blackgreenpressvest",
      "MaxPriceThreshold": 35000,
      "MinPriceThreshold": 22750,
      "SellPricePercent": -1,
      "MaxStockThreshold": 1,
      "MinStockThreshold": 1,
      "QuantityPercent": -1,
      "SpawnAttachments": [],
      "Variants": []
    },
    {
      "ClassName": "renegade_blackgreensmershvest",
      "MaxPriceThreshold": 35000,
      "MinPriceThreshold": 22750,
      "SellPricePercent": -1,
      "MaxStockThreshold": 1,
      "MinStockThreshold": 1,
      "QuantityPercent": -1,
      "SpawnAttachments": [],
      "Variants": []
    },
    {
      "ClassName": "renegade_blackorangeplatecarrier",
      "MaxPriceThreshold": 35000,
      "MinPriceThreshold": 22750,
      "SellPricePercent": -1,
      "MaxStockThreshold": 1,
      "MinStockThreshold": 1,
      "QuantityPercent": -1,
      "SpawnAttachments": [],
      "Variants": []
    },
    {
      "ClassName": "renegade_blackorangepressvest",
      "MaxPriceThreshold": 35000,
      "MinPriceThreshold": 22750,
      "SellPricePercent": -1,
      "MaxStockThreshold": 1,
      "MinStockThreshold": 1,
      "QuantityPercent": -1,
      "SpawnAttachments": [],
      "Variants": []
    },
    {
      "ClassName": "renegade_blackorangesmershvest",
      "MaxPriceThreshold": 35000,
      "MinPriceThreshold": 22750,
      "SellPricePercent": -1,
      "MaxStockThreshold": 1,
      "MinStockThreshold": 1,
      "QuantityPercent": -1,
      "SpawnAttachments": [],
      "Variants": []
    },
    {
      "ClassName": "renegade_blackpixelplatecarrier",
      "MaxPriceThreshold": 35000,
      "MinPriceThreshold": 22750,
      "SellPricePercent": -1,
      "MaxStockThreshold": 1,
      "MinStockThreshold": 1,
      "QuantityPercent": -1,
      "SpawnAttachments": [],
      "Variants": []
    },
    {
      "ClassName": "renegade_blackpixelpressvest",
      "MaxPriceThreshold": 35000,
      "MinPriceThreshold": 22750,
      "SellPricePercent": -1,
      "MaxStockThreshold": 1,
      "MinStockThreshold": 1,
      "QuantityPercent": -1,
      "SpawnAttachments": [],
      "Variants": []
    },
    {
      "ClassName": "renegade_blackpixelsmershvest",
      "MaxPriceThreshold": 35000,
      "MinPriceThreshold": 22750,
      "SellPricePercent": -1,
      "MaxStockThreshold": 1,
      "MinStockThreshold": 1,
      "QuantityPercent": -1,
      "SpawnAttachments": [],
      "Variants": []
    },
    {
      "ClassName": "renegade_blackplatecarrier",
      "MaxPriceThreshold": 35000,
      "MinPriceThreshold": 22750,
      "SellPricePercent": -1,
      "MaxStockThreshold": 1,
      "MinStockThreshold": 1,
      "QuantityPercent": -1,
      "SpawnAttachments": [],
      "Variants": []
    },
    {
      "ClassName": "renegade_blackpressvest",
      "MaxPriceThreshold": 35000,
      "MinPriceThreshold": 22750,
      "SellPricePercent": -1,
      "MaxStockThreshold": 1,
      "MinStockThreshold": 1,
      "QuantityPercent": -1,
      "SpawnAttachments": [],
      "Variants": []
    },
    {
      "ClassName": "renegade_blackscaleplatecarrier",
      "MaxPriceThreshold": 35000,
      "MinPriceThreshold": 22750,
      "SellPricePercent": -1,
      "MaxStockThreshold": 1,
      "MinStockThreshold": 1,
      "QuantityPercent": -1,
      "SpawnAttachments": [],
      "Variants": []
    },
    {
      "ClassName": "renegade_blackscalepressvest",
      "MaxPriceThreshold": 35000,
      "MinPriceThreshold": 22750,
      "SellPricePercent": -1,
      "MaxStockThreshold": 1,
      "MinStockThreshold": 1,
      "QuantityPercent": -1,
      "SpawnAttachments": [],
      "Variants": []
    },
    {
      "ClassName": "renegade_blackscalesmershvest",
      "MaxPriceThreshold": 35000,
      "MinPriceThreshold": 22750,
      "SellPricePercent": -1,
      "MaxStockThreshold": 1,
      "MinStockThreshold": 1,
      "QuantityPercent": -1,
      "SpawnAttachments": [],
      "Variants": []
    },
    {
      "ClassName": "renegade_blacksmershvest",
      "MaxPriceThreshold": 35000,
      "MinPriceThreshold": 22750,
      "SellPricePercent": -1,
      "MaxStockThreshold": 1,
      "MinStockThreshold": 1,
      "QuantityPercent": -1,
      "SpawnAttachments": [],
      "Variants": []
    },
    {
      "ClassName": "renegade_blackyellowpixelplatecarrier",
      "MaxPriceThreshold": 35000,
      "MinPriceThreshold": 22750,
      "SellPricePercent": -1,
      "MaxStockThreshold": 1,
      "MinStockThreshold": 1,
      "QuantityPercent": -1,
      "SpawnAttachments": [],
      "Variants": []
    },
    {
      "ClassName": "renegade_blackyellowpixelpressvest",
      "MaxPriceThreshold": 35000,
      "MinPriceThreshold": 22750,
      "SellPricePercent": -1,
      "MaxStockThreshold": 1,
      "MinStockThreshold": 1,
      "QuantityPercent": -1,
      "SpawnAttachments": [],
      "Variants": []
    },
    {
      "ClassName": "renegade_blackyellowpixelsmershvest",
      "MaxPriceThreshold": 35000,
      "MinPriceThreshold": 22750,
      "SellPricePercent": -1,
      "MaxStockThreshold": 1,
      "MinStockThreshold": 1,
      "QuantityPercent": -1,
      "SpawnAttachments": [],
      "Variants": []
    },
    {
      "ClassName": "renegade_bluecamopixelplatecarrier",
      "MaxPriceThreshold": 35000,
      "MinPriceThreshold": 22750,
      "SellPricePercent": -1,
      "MaxStockThreshold": 1,
      "MinStockThreshold": 1,
      "QuantityPercent": -1,
      "SpawnAttachments": [],
      "Variants": []
    },
    {
      "ClassName": "renegade_bluecamopixelpressvest",
      "MaxPriceThreshold": 35000,
      "MinPriceThreshold": 22750,
      "SellPricePercent": -1,
      "MaxStockThreshold": 1,
      "MinStockThreshold": 1,
      "QuantityPercent": -1,
      "SpawnAttachments": [],
      "Variants": []
    },
    {
      "ClassName": "renegade_bluecamopixelsmershvest",
      "MaxPriceThreshold": 35000,
      "MinPriceThreshold": 22750,
      "SellPricePercent": -1,
      "MaxStockThreshold": 1,
      "MinStockThreshold": 1,
      "QuantityPercent": -1,
      "SpawnAttachments": [],
      "Variants": []
    },
    {
      "ClassName": "renegade_bluecamoplatecarrier",
      "MaxPriceThreshold": 35000,
      "MinPriceThreshold": 22750,
      "SellPricePercent": -1,
      "MaxStockThreshold": 1,
      "MinStockThreshold": 1,
      "QuantityPercent": -1,
      "SpawnAttachments": [],
      "Variants": []
    },
    {
      "ClassName": "renegade_bluecamopressvest",
      "MaxPriceThreshold": 35000,
      "MinPriceThreshold": 22750,
      "SellPricePercent": -1,
      "MaxStockThreshold": 1,
      "MinStockThreshold": 1,
      "QuantityPercent": -1,
      "SpawnAttachments": [],
      "Variants": []
    },
    {
      "ClassName": "renegade_bluecamosmershvest",
      "MaxPriceThreshold": 35000,
      "MinPriceThreshold": 22750,
      "SellPricePercent": -1,
      "MaxStockThreshold": 1,
      "MinStockThreshold": 1,
      "QuantityPercent": -1,
      "SpawnAttachments": [],
      "Variants": []
    },
    {
      "ClassName": "renegade_bluegrunge_2platecarrier",
      "MaxPriceThreshold": 35000,
      "MinPriceThreshold": 22750,
      "SellPricePercent": -1,
      "MaxStockThreshold": 1,
      "MinStockThreshold": 1,
      "QuantityPercent": -1,
      "SpawnAttachments": [],
      "Variants": []
    },
    {
      "ClassName": "renegade_bluegrunge_2pressvest",
      "MaxPriceThreshold": 35000,
      "MinPriceThreshold": 22750,
      "SellPricePercent": -1,
      "MaxStockThreshold": 1,
      "MinStockThreshold": 1,
      "QuantityPercent": -1,
      "SpawnAttachments": [],
      "Variants": []
    },
    {
      "ClassName": "renegade_bluegrunge_2smershvest",
      "MaxPriceThreshold": 35000,
      "MinPriceThreshold": 22750,
      "SellPricePercent": -1,
      "MaxStockThreshold": 1,
      "MinStockThreshold": 1,
      "QuantityPercent": -1,
      "SpawnAttachments": [],
      "Variants": []
    },
    {
      "ClassName": "renegade_bluegrungeplatecarrier",
      "MaxPriceThreshold": 35000,
      "MinPriceThreshold": 22750,
      "SellPricePercent": -1,
      "MaxStockThreshold": 1,
      "MinStockThreshold": 1,
      "QuantityPercent": -1,
      "SpawnAttachments": [],
      "Variants": []
    },
    {
      "ClassName": "renegade_bluegrungepressvest",
      "MaxPriceThreshold": 35000,
      "MinPriceThreshold": 22750,
      "SellPricePercent": -1,
      "MaxStockThreshold": 1,
      "MinStockThreshold": 1,
      "QuantityPercent": -1,
      "SpawnAttachments": [],
      "Variants": []
    },
    {
      "ClassName": "renegade_bluegrungesmershvest",
      "MaxPriceThreshold": 35000,
      "MinPriceThreshold": 22750,
      "SellPricePercent": -1,
      "MaxStockThreshold": 1,
      "MinStockThreshold": 1,
      "QuantityPercent": -1,
      "SpawnAttachments": [],
      "Variants": []
    },
    {
      "ClassName": "renegade_bluepixelplatecarrier",
      "MaxPriceThreshold": 35000,
      "MinPriceThreshold": 22750,
      "SellPricePercent": -1,
      "MaxStockThreshold": 1,
      "MinStockThreshold": 1,
      "QuantityPercent": -1,
      "SpawnAttachments": [],
      "Variants": []
    },
    {
      "ClassName": "renegade_bluepixelpressvest",
      "MaxPriceThreshold": 35000,
      "MinPriceThreshold": 22750,
      "SellPricePercent": -1,
      "MaxStockThreshold": 1,
      "MinStockThreshold": 1,
      "QuantityPercent": -1,
      "SpawnAttachments": [],
      "Variants": []
    },
    {
      "ClassName": "renegade_bluepixelsmershvest",
      "MaxPriceThreshold": 35000,
      "MinPriceThreshold": 22750,
      "SellPricePercent": -1,
      "MaxStockThreshold": 1,
      "MinStockThreshold": 1,
      "QuantityPercent": -1,
      "SpawnAttachments": [],
      "Variants": []
    },
    {
      "ClassName": "renegade_brightgreenplatecarrier",
      "MaxPriceThreshold": 35000,
      "MinPriceThreshold": 22750,
      "SellPricePercent": -1,
      "MaxStockThreshold": 1,
      "MinStockThreshold": 1,
      "QuantityPercent": -1,
      "SpawnAttachments": [],
      "Variants": []
    },
    {
      "ClassName": "renegade_brightgreenpressvest",
      "MaxPriceThreshold": 35000,
      "MinPriceThreshold": 22750,
      "SellPricePercent": -1,
      "MaxStockThreshold": 1,
      "MinStockThreshold": 1,
      "QuantityPercent": -1,
      "SpawnAttachments": [],
      "Variants": []
    },
    {
      "ClassName": "renegade_brightgreensmershvest",
      "MaxPriceThreshold": 35000,
      "MinPriceThreshold": 22750,
      "SellPricePercent": -1,
      "MaxStockThreshold": 1,
      "MinStockThreshold": 1,
      "QuantityPercent": -1,
      "SpawnAttachments": [],
      "Variants": []
    },
    {
      "ClassName": "renegade_camo1platecarrier",
      "MaxPriceThreshold": 35000,
      "MinPriceThreshold": 22750,
      "SellPricePercent": -1,
      "MaxStockThreshold": 1,
      "MinStockThreshold": 1,
      "QuantityPercent": -1,
      "SpawnAttachments": [],
      "Variants": []
    },
    {
      "ClassName": "renegade_camo1pressvest",
      "MaxPriceThreshold": 35000,
      "MinPriceThreshold": 22750,
      "SellPricePercent": -1,
      "MaxStockThreshold": 1,
      "MinStockThreshold": 1,
      "QuantityPercent": -1,
      "SpawnAttachments": [],
      "Variants": []
    },
    {
      "ClassName": "renegade_camo1smershvest",
      "MaxPriceThreshold": 35000,
      "MinPriceThreshold": 22750,
      "SellPricePercent": -1,
      "MaxStockThreshold": 1,
      "MinStockThreshold": 1,
      "QuantityPercent": -1,
      "SpawnAttachments": [],
      "Variants": []
    },
    {
      "ClassName": "renegade_camoscaleplatecarrier",
      "MaxPriceThreshold": 35000,
      "MinPriceThreshold": 22750,
      "SellPricePercent": -1,
      "MaxStockThreshold": 1,
      "MinStockThreshold": 1,
      "QuantityPercent": -1,
      "SpawnAttachments": [],
      "Variants": []
    },
    {
      "ClassName": "renegade_camoscalepressvest",
      "MaxPriceThreshold": 35000,
      "MinPriceThreshold": 22750,
      "SellPricePercent": -1,
      "MaxStockThreshold": 1,
      "MinStockThreshold": 1,
      "QuantityPercent": -1,
      "SpawnAttachments": [],
      "Variants": []
    },
    {
      "ClassName": "renegade_camoscalesmershvest",
      "MaxPriceThreshold": 35000,
      "MinPriceThreshold": 22750,
      "SellPricePercent": -1,
      "MaxStockThreshold": 1,
      "MinStockThreshold": 1,
      "QuantityPercent": -1,
      "SpawnAttachments": [],
      "Variants": []
    },
    {
      "ClassName": "renegade_darkcamoplatecarrier",
      "MaxPriceThreshold": 35000,
      "MinPriceThreshold": 22750,
      "SellPricePercent": -1,
      "MaxStockThreshold": 1,
      "MinStockThreshold": 1,
      "QuantityPercent": -1,
      "SpawnAttachments": [],
      "Variants": []
    },
    {
      "ClassName": "renegade_darkcamopressvest",
      "MaxPriceThreshold": 35000,
      "MinPriceThreshold": 22750,
      "SellPricePercent": -1,
      "MaxStockThreshold": 1,
      "MinStockThreshold": 1,
      "QuantityPercent": -1,
      "SpawnAttachments": [],
      "Variants": []
    },
    {
      "ClassName": "renegade_darkcamosmershvest",
      "MaxPriceThreshold": 35000,
      "MinPriceThreshold": 22750,
      "SellPricePercent": -1,
      "MaxStockThreshold": 1,
      "MinStockThreshold": 1,
      "QuantityPercent": -1,
      "SpawnAttachments": [],
      "Variants": []
    },
    {
      "ClassName": "renegade_forestgreenplatecarrier",
      "MaxPriceThreshold": 35000,
      "MinPriceThreshold": 22750,
      "SellPricePercent": -1,
      "MaxStockThreshold": 1,
      "MinStockThreshold": 1,
      "QuantityPercent": -1,
      "SpawnAttachments": [],
      "Variants": []
    },
    {
      "ClassName": "renegade_forestgreenpressvest",
      "MaxPriceThreshold": 35000,
      "MinPriceThreshold": 22750,
      "SellPricePercent": -1,
      "MaxStockThreshold": 1,
      "MinStockThreshold": 1,
      "QuantityPercent": -1,
      "SpawnAttachments": [],
      "Variants": []
    },
    {
      "ClassName": "renegade_forestgreensmershvest",
      "MaxPriceThreshold": 35000,
      "MinPriceThreshold": 22750,
      "SellPricePercent": -1,
      "MaxStockThreshold": 1,
      "MinStockThreshold": 1,
      "QuantityPercent": -1,
      "SpawnAttachments": [],
      "Variants": []
    },
    {
      "ClassName": "renegade_forestplatecarrier",
      "MaxPriceThreshold": 35000,
      "MinPriceThreshold": 22750,
      "SellPricePercent": -1,
      "MaxStockThreshold": 1,
      "MinStockThreshold": 1,
      "QuantityPercent": -1,
      "SpawnAttachments": [],
      "Variants": []
    },
    {
      "ClassName": "renegade_forestpressvest",
      "MaxPriceThreshold": 35000,
      "MinPriceThreshold": 22750,
      "SellPricePercent": -1,
      "MaxStockThreshold": 1,
      "MinStockThreshold": 1,
      "QuantityPercent": -1,
      "SpawnAttachments": [],
      "Variants": []
    },
    {
      "ClassName": "renegade_forestsmershvest",
      "MaxPriceThreshold": 35000,
      "MinPriceThreshold": 22750,
      "SellPricePercent": -1,
      "MaxStockThreshold": 1,
      "MinStockThreshold": 1,
      "QuantityPercent": -1,
      "SpawnAttachments": [],
      "Variants": []
    },
    {
      "ClassName": "renegade_galaxyplatecarrier",
      "MaxPriceThreshold": 35000,
      "MinPriceThreshold": 22750,
      "SellPricePercent": -1,
      "MaxStockThreshold": 1,
      "MinStockThreshold": 1,
      "QuantityPercent": -1,
      "SpawnAttachments": [],
      "Variants": []
    },
    {
      "ClassName": "renegade_galaxypressvest",
      "MaxPriceThreshold": 35000,
      "MinPriceThreshold": 22750,
      "SellPricePercent": -1,
      "MaxStockThreshold": 1,
      "MinStockThreshold": 1,
      "QuantityPercent": -1,
      "SpawnAttachments": [],
      "Variants": []
    },
    {
      "ClassName": "renegade_galaxysmershvest",
      "MaxPriceThreshold": 35000,
      "MinPriceThreshold": 22750,
      "SellPricePercent": -1,
      "MaxStockThreshold": 1,
      "MinStockThreshold": 1,
      "QuantityPercent": -1,
      "SpawnAttachments": [],
      "Variants": []
    },
    {
      "ClassName": "renegade_greencamo_2platecarrier",
      "MaxPriceThreshold": 35000,
      "MinPriceThreshold": 22750,
      "SellPricePercent": -1,
      "MaxStockThreshold": 1,
      "MinStockThreshold": 1,
      "QuantityPercent": -1,
      "SpawnAttachments": [],
      "Variants": []
    },
    {
      "ClassName": "renegade_greencamo_2pressvest",
      "MaxPriceThreshold": 35000,
      "MinPriceThreshold": 22750,
      "SellPricePercent": -1,
      "MaxStockThreshold": 1,
      "MinStockThreshold": 1,
      "QuantityPercent": -1,
      "SpawnAttachments": [],
      "Variants": []
    },
    {
      "ClassName": "renegade_greencamo_2smershvest",
      "MaxPriceThreshold": 35000,
      "MinPriceThreshold": 22750,
      "SellPricePercent": -1,
      "MaxStockThreshold": 1,
      "MinStockThreshold": 1,
      "QuantityPercent": -1,
      "SpawnAttachments": [],
      "Variants": []
    },
    {
      "ClassName": "renegade_greencamo_3platecarrier",
      "MaxPriceThreshold": 35000,
      "MinPriceThreshold": 22750,
      "SellPricePercent": -1,
      "MaxStockThreshold": 1,
      "MinStockThreshold": 1,
      "QuantityPercent": -1,
      "SpawnAttachments": [],
      "Variants": []
    },
    {
      "ClassName": "renegade_greencamo_3pressvest",
      "MaxPriceThreshold": 35000,
      "MinPriceThreshold": 22750,
      "SellPricePercent": -1,
      "MaxStockThreshold": 1,
      "MinStockThreshold": 1,
      "QuantityPercent": -1,
      "SpawnAttachments": [],
      "Variants": []
    },
    {
      "ClassName": "renegade_greencamo_3smershvest",
      "MaxPriceThreshold": 35000,
      "MinPriceThreshold": 22750,
      "SellPricePercent": -1,
      "MaxStockThreshold": 1,
      "MinStockThreshold": 1,
      "QuantityPercent": -1,
      "SpawnAttachments": [],
      "Variants": []
    },
    {
      "ClassName": "renegade_greencamo_4platecarrier",
      "MaxPriceThreshold": 35000,
      "MinPriceThreshold": 22750,
      "SellPricePercent": -1,
      "MaxStockThreshold": 1,
      "MinStockThreshold": 1,
      "QuantityPercent": -1,
      "SpawnAttachments": [],
      "Variants": []
    },
    {
      "ClassName": "renegade_greencamo_4pressvest",
      "MaxPriceThreshold": 35000,
      "MinPriceThreshold": 22750,
      "SellPricePercent": -1,
      "MaxStockThreshold": 1,
      "MinStockThreshold": 1,
      "QuantityPercent": -1,
      "SpawnAttachments": [],
      "Variants": []
    },
    {
      "ClassName": "renegade_greencamo_4smershvest",
      "MaxPriceThreshold": 35000,
      "MinPriceThreshold": 22750,
      "SellPricePercent": -1,
      "MaxStockThreshold": 1,
      "MinStockThreshold": 1,
      "QuantityPercent": -1,
      "SpawnAttachments": [],
      "Variants": []
    },
    {
      "ClassName": "renegade_greencamoplatecarrier",
      "MaxPriceThreshold": 35000,
      "MinPriceThreshold": 22750,
      "SellPricePercent": -1,
      "MaxStockThreshold": 1,
      "MinStockThreshold": 1,
      "QuantityPercent": -1,
      "SpawnAttachments": [],
      "Variants": []
    },
    {
      "ClassName": "renegade_greencamopressvest",
      "MaxPriceThreshold": 35000,
      "MinPriceThreshold": 22750,
      "SellPricePercent": -1,
      "MaxStockThreshold": 1,
      "MinStockThreshold": 1,
      "QuantityPercent": -1,
      "SpawnAttachments": [],
      "Variants": []
    },
    {
      "ClassName": "renegade_greencamosmershvest",
      "MaxPriceThreshold": 35000,
      "MinPriceThreshold": 22750,
      "SellPricePercent": -1,
      "MaxStockThreshold": 1,
      "MinStockThreshold": 1,
      "QuantityPercent": -1,
      "SpawnAttachments": [],
      "Variants": []
    },
    {
      "ClassName": "renegade_greenpixelplatecarrier",
      "MaxPriceThreshold": 35000,
      "MinPriceThreshold": 22750,
      "SellPricePercent": -1,
      "MaxStockThreshold": 1,
      "MinStockThreshold": 1,
      "QuantityPercent": -1,
      "SpawnAttachments": [],
      "Variants": []
    },
    {
      "ClassName": "renegade_greenpixelpressvest",
      "MaxPriceThreshold": 35000,
      "MinPriceThreshold": 22750,
      "SellPricePercent": -1,
      "MaxStockThreshold": 1,
      "MinStockThreshold": 1,
      "QuantityPercent": -1,
      "SpawnAttachments": [],
      "Variants": []
    },
    {
      "ClassName": "renegade_greenpixelsmershvest",
      "MaxPriceThreshold": 35000,
      "MinPriceThreshold": 22750,
      "SellPricePercent": -1,
      "MaxStockThreshold": 1,
      "MinStockThreshold": 1,
      "QuantityPercent": -1,
      "SpawnAttachments": [],
      "Variants": []
    },
    {
      "ClassName": "renegade_lightcamoplatecarrier",
      "MaxPriceThreshold": 35000,
      "MinPriceThreshold": 22750,
      "SellPricePercent": -1,
      "MaxStockThreshold": 1,
      "MinStockThreshold": 1,
      "QuantityPercent": -1,
      "SpawnAttachments": [],
      "Variants": []
    },
    {
      "ClassName": "renegade_lightcamopressvest",
      "MaxPriceThreshold": 35000,
      "MinPriceThreshold": 22750,
      "SellPricePercent": -1,
      "MaxStockThreshold": 1,
      "MinStockThreshold": 1,
      "QuantityPercent": -1,
      "SpawnAttachments": [],
      "Variants": []
    },
    {
      "ClassName": "renegade_lightcamosmershvest",
      "MaxPriceThreshold": 35000,
      "MinPriceThreshold": 22750,
      "SellPricePercent": -1,
      "MaxStockThreshold": 1,
      "MinStockThreshold": 1,
      "QuantityPercent": -1,
      "SpawnAttachments": [],
      "Variants": []
    },
    {
      "ClassName": "renegade_militarycamo_2platecarrier",
      "MaxPriceThreshold": 35000,
      "MinPriceThreshold": 22750,
      "SellPricePercent": -1,
      "MaxStockThreshold": 1,
      "MinStockThreshold": 1,
      "QuantityPercent": -1,
      "SpawnAttachments": [],
      "Variants": []
    },
    {
      "ClassName": "renegade_militarycamo_2pressvest",
      "MaxPriceThreshold": 35000,
      "MinPriceThreshold": 22750,
      "SellPricePercent": -1,
      "MaxStockThreshold": 1,
      "MinStockThreshold": 1,
      "QuantityPercent": -1,
      "SpawnAttachments": [],
      "Variants": []
    },
    {
      "ClassName": "renegade_militarycamo_2smershvest",
      "MaxPriceThreshold": 35000,
      "MinPriceThreshold": 22750,
      "SellPricePercent": -1,
      "MaxStockThreshold": 1,
      "MinStockThreshold": 1,
      "QuantityPercent": -1,
      "SpawnAttachments": [],
      "Variants": []
    },
    {
      "ClassName": "renegade_militarycamoplatecarrier",
      "MaxPriceThreshold": 35000,
      "MinPriceThreshold": 22750,
      "SellPricePercent": -1,
      "MaxStockThreshold": 1,
      "MinStockThreshold": 1,
      "QuantityPercent": -1,
      "SpawnAttachments": [],
      "Variants": []
    },
    {
      "ClassName": "renegade_militarycamopressvest",
      "MaxPriceThreshold": 35000,
      "MinPriceThreshold": 22750,
      "SellPricePercent": -1,
      "MaxStockThreshold": 1,
      "MinStockThreshold": 1,
      "QuantityPercent": -1,
      "SpawnAttachments": [],
      "Variants": []
    },
    {
      "ClassName": "renegade_militarycamosmershvest",
      "MaxPriceThreshold": 35000,
      "MinPriceThreshold": 22750,
      "SellPricePercent": -1,
      "MaxStockThreshold": 1,
      "MinStockThreshold": 1,
      "QuantityPercent": -1,
      "SpawnAttachments": [],
      "Variants": []
    },
    {
      "ClassName": "renegade_navygoldplatecarrier",
      "MaxPriceThreshold": 39500,
      "MinPriceThreshold": 25675,
      "SellPricePercent": -1,
      "MaxStockThreshold": 1,
      "MinStockThreshold": 1,
      "QuantityPercent": -1,
      "SpawnAttachments": [],
      "Variants": []
    },
    {
      "ClassName": "renegade_navygoldpressvest",
      "MaxPriceThreshold": 39500,
      "MinPriceThreshold": 25675,
      "SellPricePercent": -1,
      "MaxStockThreshold": 1,
      "MinStockThreshold": 1,
      "QuantityPercent": -1,
      "SpawnAttachments": [],
      "Variants": []
    },
    {
      "ClassName": "renegade_navygoldsmershvest",
      "MaxPriceThreshold": 39500,
      "MinPriceThreshold": 25675,
      "SellPricePercent": -1,
      "MaxStockThreshold": 1,
      "MinStockThreshold": 1,
      "QuantityPercent": -1,
      "SpawnAttachments": [],
      "Variants": []
    },
    {
      "ClassName": "renegade_orangecamoplatecarrier",
      "MaxPriceThreshold": 35000,
      "MinPriceThreshold": 22750,
      "SellPricePercent": -1,
      "MaxStockThreshold": 1,
      "MinStockThreshold": 1,
      "QuantityPercent": -1,
      "SpawnAttachments": [],
      "Variants": []
    },
    {
      "ClassName": "renegade_orangecamopressvest",
      "MaxPriceThreshold": 35000,
      "MinPriceThreshold": 22750,
      "SellPricePercent": -1,
      "MaxStockThreshold": 1,
      "MinStockThreshold": 1,
      "QuantityPercent": -1,
      "SpawnAttachments": [],
      "Variants": []
    },
    {
      "ClassName": "renegade_orangecamosmershvest",
      "MaxPriceThreshold": 35000,
      "MinPriceThreshold": 22750,
      "SellPricePercent": -1,
      "MaxStockThreshold": 1,
      "MinStockThreshold": 1,
      "QuantityPercent": -1,
      "SpawnAttachments": [],
      "Variants": []
    },
    {
      "ClassName": "renegade_orangelinesplatecarrier",
      "MaxPriceThreshold": 35000,
      "MinPriceThreshold": 22750,
      "SellPricePercent": -1,
      "MaxStockThreshold": 1,
      "MinStockThreshold": 1,
      "QuantityPercent": -1,
      "SpawnAttachments": [],
      "Variants": []
    },
    {
      "ClassName": "renegade_orangelinespressvest",
      "MaxPriceThreshold": 35000,
      "MinPriceThreshold": 22750,
      "SellPricePercent": -1,
      "MaxStockThreshold": 1,
      "MinStockThreshold": 1,
      "QuantityPercent": -1,
      "SpawnAttachments": [],
      "Variants": []
    },
    {
      "ClassName": "renegade_orangelinessmershvest",
      "MaxPriceThreshold": 35000,
      "MinPriceThreshold": 22750,
      "SellPricePercent": -1,
      "MaxStockThreshold": 1,
      "MinStockThreshold": 1,
      "QuantityPercent": -1,
      "SpawnAttachments": [],
      "Variants": []
    },
    {
      "ClassName": "renegade_pinkcamoplatecarrier",
      "MaxPriceThreshold": 35000,
      "MinPriceThreshold": 22750,
      "SellPricePercent": -1,
      "MaxStockThreshold": 1,
      "MinStockThreshold": 1,
      "QuantityPercent": -1,
      "SpawnAttachments": [],
      "Variants": []
    },
    {
      "ClassName": "renegade_pinkcamopressvest",
      "MaxPriceThreshold": 35000,
      "MinPriceThreshold": 22750,
      "SellPricePercent": -1,
      "MaxStockThreshold": 1,
      "MinStockThreshold": 1,
      "QuantityPercent": -1,
      "SpawnAttachments": [],
      "Variants": []
    },
    {
      "ClassName": "renegade_pinkcamosmershvest",
      "MaxPriceThreshold": 35000,
      "MinPriceThreshold": 22750,
      "SellPricePercent": -1,
      "MaxStockThreshold": 1,
      "MinStockThreshold": 1,
      "QuantityPercent": -1,
      "SpawnAttachments": [],
      "Variants": []
    },
    {
      "ClassName": "renegade_pureblackplatecarrier",
      "MaxPriceThreshold": 35000,
      "MinPriceThreshold": 22750,
      "SellPricePercent": -1,
      "MaxStockThreshold": 1,
      "MinStockThreshold": 1,
      "QuantityPercent": -1,
      "SpawnAttachments": [],
      "Variants": []
    },
    {
      "ClassName": "renegade_pureblackpressvest",
      "MaxPriceThreshold": 35000,
      "MinPriceThreshold": 22750,
      "SellPricePercent": -1,
      "MaxStockThreshold": 1,
      "MinStockThreshold": 1,
      "QuantityPercent": -1,
      "SpawnAttachments": [],
      "Variants": []
    },
    {
      "ClassName": "renegade_pureblacksmershvest",
      "MaxPriceThreshold": 35000,
      "MinPriceThreshold": 22750,
      "SellPricePercent": -1,
      "MaxStockThreshold": 1,
      "MinStockThreshold": 1,
      "QuantityPercent": -1,
      "SpawnAttachments": [],
      "Variants": []
    },
    {
      "ClassName": "renegade_redcamoplatecarrier",
      "MaxPriceThreshold": 35000,
      "MinPriceThreshold": 22750,
      "SellPricePercent": -1,
      "MaxStockThreshold": 1,
      "MinStockThreshold": 1,
      "QuantityPercent": -1,
      "SpawnAttachments": [],
      "Variants": []
    },
    {
      "ClassName": "renegade_redcamopressvest",
      "MaxPriceThreshold": 35000,
      "MinPriceThreshold": 22750,
      "SellPricePercent": -1,
      "MaxStockThreshold": 1,
      "MinStockThreshold": 1,
      "QuantityPercent": -1,
      "SpawnAttachments": [],
      "Variants": []
    },
    {
      "ClassName": "renegade_redcamosmershvest",
      "MaxPriceThreshold": 35000,
      "MinPriceThreshold": 22750,
      "SellPricePercent": -1,
      "MaxStockThreshold": 1,
      "MinStockThreshold": 1,
      "QuantityPercent": -1,
      "SpawnAttachments": [],
      "Variants": []
    },
    {
      "ClassName": "renegade_redgreycamoplatecarrier",
      "MaxPriceThreshold": 35000,
      "MinPriceThreshold": 22750,
      "SellPricePercent": -1,
      "MaxStockThreshold": 1,
      "MinStockThreshold": 1,
      "QuantityPercent": -1,
      "SpawnAttachments": [],
      "Variants": []
    },
    {
      "ClassName": "renegade_redgreycamopressvest",
      "MaxPriceThreshold": 35000,
      "MinPriceThreshold": 22750,
      "SellPricePercent": -1,
      "MaxStockThreshold": 1,
      "MinStockThreshold": 1,
      "QuantityPercent": -1,
      "SpawnAttachments": [],
      "Variants": []
    },
    {
      "ClassName": "renegade_redgreycamosmershvest",
      "MaxPriceThreshold": 35000,
      "MinPriceThreshold": 22750,
      "SellPricePercent": -1,
      "MaxStockThreshold": 1,
      "MinStockThreshold": 1,
      "QuantityPercent": -1,
      "SpawnAttachments": [],
      "Variants": []
    },
    {
      "ClassName": "renegade_redscaleplatecarrier",
      "MaxPriceThreshold": 35000,
      "MinPriceThreshold": 22750,
      "SellPricePercent": -1,
      "MaxStockThreshold": 1,
      "MinStockThreshold": 1,
      "QuantityPercent": -1,
      "SpawnAttachments": [],
      "Variants": []
    },
    {
      "ClassName": "renegade_redscalepressvest",
      "MaxPriceThreshold": 35000,
      "MinPriceThreshold": 22750,
      "SellPricePercent": -1,
      "MaxStockThreshold": 1,
      "MinStockThreshold": 1,
      "QuantityPercent": -1,
      "SpawnAttachments": [],
      "Variants": []
    },
    {
      "ClassName": "renegade_redscalesmershvest",
      "MaxPriceThreshold": 35000,
      "MinPriceThreshold": 22750,
      "SellPricePercent": -1,
      "MaxStockThreshold": 1,
      "MinStockThreshold": 1,
      "QuantityPercent": -1,
      "SpawnAttachments": [],
      "Variants": []
    },
    {
      "ClassName": "renegade_whitecamoplatecarrier",
      "MaxPriceThreshold": 35000,
      "MinPriceThreshold": 22750,
      "SellPricePercent": -1,
      "MaxStockThreshold": 1,
      "MinStockThreshold": 1,
      "QuantityPercent": -1,
      "SpawnAttachments": [],
      "Variants": []
    },
    {
      "ClassName": "renegade_whitecamopressvest",
      "MaxPriceThreshold": 35000,
      "MinPriceThreshold": 22750,
      "SellPricePercent": -1,
      "MaxStockThreshold": 1,
      "MinStockThreshold": 1,
      "QuantityPercent": -1,
      "SpawnAttachments": [],
      "Variants": []
    },
    {
      "ClassName": "renegade_whitecamosmershvest",
      "MaxPriceThreshold": 35000,
      "MinPriceThreshold": 22750,
      "SellPricePercent": -1,
      "MaxStockThreshold": 1,
      "MinStockThreshold": 1,
      "QuantityPercent": -1,
      "SpawnAttachments": [],
      "Variants": []
    }
  ]
}